{
  "id": "hk_traffic_medium_003",
  "dataset": "HK Traffic Digest",
  "domain": "transportation",
  "tier": "medium",
  "rows": 10,
  "cols": 5,
  "columns": [
    "Entity",
    "Accidents_monthly",
    "Bus_passengers",
    "Peak_hour_flow",
    "Avg_speed_kmh"
  ],
  "data": [
    {
      "Entity": "Route_Q17",
      "Accidents_monthly": 25.1,
      "Bus_passengers": 5749.8,
      "Peak_hour_flow": 11029.0,
      "Avg_speed_kmh": 50.1
    },
    {
      "Entity": "Route_K11",
      "Accidents_monthly": 22.9,
      "Bus_passengers": 45113.6,
      "Peak_hour_flow": 21523.7,
      "Avg_speed_kmh": 46.3
    },
    {
      "Entity": "Route_M13",
      "Accidents_monthly": 6.6,
      "Bus_passengers": 36559.3,
      "Peak_hour_flow": 28795.2,
      "Avg_speed_kmh": 52.2
    },
    {
      "Entity": "Route_F6",
      "Accidents_monthly": 12.2,
      "Bus_passengers": 4362.4,
      "Peak_hour_flow": 18450.6,
      "Avg_speed_kmh": 18.2
    },
    {
      "Entity": "Route_J10",
      "Accidents_monthly": 24.7,
      "Bus_passengers": 34900.5,
      "Peak_hour_flow": 20601.7,
      "Avg_speed_kmh": 41.3
    },
    {
      "Entity": "Route_E5",
      "Accidents_monthly": 4.9,
      "Bus_passengers": 31949.8,
      "Peak_hour_flow": 14239.6,
      "Avg_speed_kmh": 52.9
    },
    {
      "Entity": "Route_L12",
      "Accidents_monthly": 42.1,
      "Bus_passengers": 38110.1,
      "Peak_hour_flow": 23171.4,
      "Avg_speed_kmh": 53.0
    },
    {
      "Entity": "Route_A1",
      "Accidents_monthly": 7.3,
      "Bus_passengers": 41581.7,
      "Peak_hour_flow": 29934.7,
      "Avg_speed_kmh": 57.7
    },
    {
      "Entity": "Route_S19",
      "Accidents_monthly": 10.5,
      "Bus_passengers": 36199.2,
      "Peak_hour_flow": 6490.9,
      "Avg_speed_kmh": 61.8
    },
    {
      "Entity": "Route_H8",
      "Accidents_monthly": 34.9,
      "Bus_passengers": 29722.6,
      "Peak_hour_flow": 7667.3,
      "Avg_speed_kmh": 56.7
    }
  ],
  "index_col": "Entity",
  "metric_cols": [
    "Accidents_monthly",
    "Bus_passengers",
    "Peak_hour_flow",
    "Avg_speed_kmh"
  ]
}